<?xml version="1.0" encoding="UTF-8"?>
<mule xmlns:ee="http://www.mulesoft.org/schema/mule/ee/core" xmlns:doc="http://www.mulesoft.org/schema/mule/documentation" xmlns="http://www.mulesoft.org/schema/mule/core" xmlns:apikit="http://www.mulesoft.org/schema/mule/mule-apikit" xmlns:http="http://www.mulesoft.org/schema/mule/http" xmlns:xsi="http://www.w3.org/2001/XMLSchema-instance" xsi:schemaLocation="http://www.mulesoft.org/schema/mule/core http://www.mulesoft.org/schema/mule/core/current/mule.xsd http://www.mulesoft.org/schema/mule/http http://www.mulesoft.org/schema/mule/http/current/mule-http.xsd http://www.mulesoft.org/schema/mule/mule-apikit http://www.mulesoft.org/schema/mule/mule-apikit/current/mule-apikit.xsd 
http://www.mulesoft.org/schema/mule/ee/core http://www.mulesoft.org/schema/mule/ee/core/current/mule-ee.xsd">
    
    <apikit:config name="american-flights-system-api-config" raml="american-flights-system-api.raml" outboundHeadersMapName="outboundHeaders" httpStatusVarName="httpStatus" />
    <flow name="american-flights-system-api-main">
        <http:listener config-ref="american-flights-system-api-httpListenerConfig" path="/api/*">
            <http:response statusCode="#[vars.httpStatus default 200]">
            </http:response>
            <http:error-response statusCode="#[vars.httpStatus default 500]">
                <http:body><![CDATA[#[payload]]]></http:body>
            </http:error-response>
        </http:listener>
        <apikit:router config-ref="american-flights-system-api-config" />
        <error-handler>
            <on-error-propagate type="APIKIT:BAD_REQUEST">
                <ee:transform xmlns:ee="http://www.mulesoft.org/schema/mule/ee/core" xsi:schemaLocation="http://www.mulesoft.org/schema/mule/ee/core http://www.mulesoft.org/schema/mule/ee/core/current/mule-ee.xsd">
                    <ee:message>
                        <ee:set-payload><![CDATA[%dw 2.0
output application/json
---
{message: "Bad request"}]]></ee:set-payload>
                    </ee:message>
                    <ee:variables>
                        <ee:set-variable variableName="httpStatus">400</ee:set-variable>
                    </ee:variables>
                </ee:transform>
            </on-error-propagate>
            <on-error-propagate type="APIKIT:NOT_FOUND">
                <ee:transform xmlns:ee="http://www.mulesoft.org/schema/mule/ee/core" xsi:schemaLocation="http://www.mulesoft.org/schema/mule/ee/core http://www.mulesoft.org/schema/mule/ee/core/current/mule-ee.xsd">
                    <ee:message>
                        <ee:set-payload><![CDATA[%dw 2.0
output application/json
---
{message: "Resource not found"}]]></ee:set-payload>
                    </ee:message>
                    <ee:variables>
                        <ee:set-variable variableName="httpStatus">404</ee:set-variable>
                    </ee:variables>
                </ee:transform>
            </on-error-propagate>
            <on-error-propagate type="APIKIT:METHOD_NOT_ALLOWED">
                <ee:transform xmlns:ee="http://www.mulesoft.org/schema/mule/ee/core" xsi:schemaLocation="http://www.mulesoft.org/schema/mule/ee/core http://www.mulesoft.org/schema/mule/ee/core/current/mule-ee.xsd">
                    <ee:message>
                        <ee:set-payload><![CDATA[%dw 2.0
output application/json
---
{message: "Method not allowed"}]]></ee:set-payload>
                    </ee:message>
                    <ee:variables>
                        <ee:set-variable variableName="httpStatus">405</ee:set-variable>
                    </ee:variables>
                </ee:transform>
            </on-error-propagate>
            <on-error-propagate type="APIKIT:NOT_ACCEPTABLE">
                <ee:transform xmlns:ee="http://www.mulesoft.org/schema/mule/ee/core" xsi:schemaLocation="http://www.mulesoft.org/schema/mule/ee/core http://www.mulesoft.org/schema/mule/ee/core/current/mule-ee.xsd">
                    <ee:message>
                        <ee:set-payload><![CDATA[%dw 2.0
output application/json
---
{message: "Not acceptable"}]]></ee:set-payload>
                    </ee:message>
                    <ee:variables>
                        <ee:set-variable variableName="httpStatus">406</ee:set-variable>
                    </ee:variables>
                </ee:transform>
            </on-error-propagate>
            <on-error-propagate type="APIKIT:UNSUPPORTED_MEDIA_TYPE">
                <ee:transform xmlns:ee="http://www.mulesoft.org/schema/mule/ee/core" xsi:schemaLocation="http://www.mulesoft.org/schema/mule/ee/core http://www.mulesoft.org/schema/mule/ee/core/current/mule-ee.xsd">
                    <ee:message>
                        <ee:set-payload><![CDATA[%dw 2.0
output application/json
---
{message: "Unsupported media type"}]]></ee:set-payload>
                    </ee:message>
                    <ee:variables>
                        <ee:set-variable variableName="httpStatus">415</ee:set-variable>
                    </ee:variables>
                </ee:transform>
            </on-error-propagate>
            <on-error-propagate type="APIKIT:NOT_IMPLEMENTED">
                <ee:transform xmlns:ee="http://www.mulesoft.org/schema/mule/ee/core" xsi:schemaLocation="http://www.mulesoft.org/schema/mule/ee/core http://www.mulesoft.org/schema/mule/ee/core/current/mule-ee.xsd">
                    <ee:message>
                        <ee:set-payload><![CDATA[%dw 2.0
output application/json
---
{message: "Not Implemented"}]]></ee:set-payload>
                    </ee:message>
                    <ee:variables>
                        <ee:set-variable variableName="httpStatus">501</ee:set-variable>
                    </ee:variables>
                </ee:transform>
            </on-error-propagate>
        </error-handler>
    </flow>
    <flow name="american-flights-system-api-console">
        <http:listener config-ref="american-flights-system-api-httpListenerConfig" path="/console/*">
            <http:response statusCode="#[vars.httpStatus default 200]">
                <http:headers>#[vars.outboundHeaders default {}]</http:headers>
            </http:response>
            <http:error-response statusCode="#[vars.httpStatus default 500]">
                <http:body>#[payload]</http:body>
                <http:headers>#[vars.outboundHeaders default {}]</http:headers>
            </http:error-response>
        </http:listener>
        <apikit:console config-ref="american-flights-system-api-config" />
        <error-handler>
            <on-error-propagate type="APIKIT:NOT_FOUND">
                <ee:transform xmlns:ee="http://www.mulesoft.org/schema/mule/ee/core" xsi:schemaLocation="http://www.mulesoft.org/schema/mule/ee/core http://www.mulesoft.org/schema/mule/ee/core/current/mule-ee.xsd">
                    <ee:message>
                        <ee:set-payload><![CDATA[%dw 2.0
output application/json
---
{message: "Resource not found"}]]></ee:set-payload>
                    </ee:message>
                    <ee:variables>
                        <ee:set-variable variableName="httpStatus">404</ee:set-variable>
                    </ee:variables>
                </ee:transform>
            </on-error-propagate>
        </error-handler>
    </flow>
    <flow name="put:\flights\(ID):application\json:american-flights-system-api-config">
        <ee:transform xmlns:ee="http://www.mulesoft.org/schema/mule/ee/core" doc:id="e990b972-94fc-41d8-9dd8-750c85c9e5b0">
            <ee:variables>
                <ee:set-variable variableName="ID"><![CDATA[attributes.uriParams.ID]]></ee:set-variable>
            </ee:variables>
        </ee:transform>
		<flow-ref doc:name="process_UpdateFlightFlowReference" doc:id="f5303540-197a-432d-8de4-5b215acc2314" name="process_UpdateFlightFlow"/>
    </flow>
    <flow name="delete:\flights\(ID):american-flights-system-api-config">
		<ee:transform doc:name="Transform Message" doc:id="78fd4c92-6166-49a6-aa2e-2d534788c4a9">
			<ee:variables>
				<ee:set-variable variableName="ID"><![CDATA[attributes.uriParams.ID]]></ee:set-variable>
			</ee:variables>
		</ee:transform>
		<flow-ref doc:name="process_DeleteFlightFlowReference" doc:id="ad674b08-6b18-4c82-a47d-aebfbacfa638" name="process_DeleteFlightFlow"/>
    </flow>
    <flow name="get:\flights:american-flights-system-api-config">
		<ee:transform doc:name="Transform Message" doc:id="474ade41-077a-41a5-bcd8-206335675662" >
			<ee:message >
			</ee:message>
			<ee:variables >
				<ee:set-variable variableName="destination" ><![CDATA[attributes.queryParams.destination]]></ee:set-variable>
			</ee:variables>
		</ee:transform>
		<flow-ref doc:name="process_GetFlightsByDestinationFlowReference" doc:id="a72c3072-3e76-4260-a22c-7e9d35b06ce4" name="process_GetFlightsByDestinationFlow"/>
    </flow>
    <flow name="get:\flights\(ID):american-flights-system-api-config">
        <ee:transform xmlns:ee="http://www.mulesoft.org/schema/mule/ee/core" doc:id="01ff8d00-fb8c-4280-9396-0a0608ea978e">
            <ee:variables>
                <ee:set-variable variableName="ID"><![CDATA[attributes.uriParams.ID]]></ee:set-variable>
            </ee:variables>
        </ee:transform>
		<flow-ref doc:name="process_GetFlightByIDReference" doc:id="33b44515-bce1-4fc5-8d06-7d7fc2f67659" name="process_GetFlightByID"/>
    </flow>
    <flow name="post:\flights:application\json:american-flights-system-api-config">
		<flow-ref doc:name="process_CreateFlightFlowReference" doc:id="12f18ea8-41a0-4132-b35f-babdfbe26460" name="process_CreateFlightFlow"/>
    </flow>
</mule>
